vnpy_timescaledb/__init__.py
vnpy_timescaledb/timescaledb_database.py
vnpy_timescaledb/timescaledb_scripts.py
vnpy_timescaledb-1.0.1.dist-info/LICENSE
vnpy_timescaledb-1.0.1.dist-info/METADATA
vnpy_timescaledb-1.0.1.dist-info/WHEEL
vnpy_timescaledb-1.0.1.dist-info/top_level.txt
vnpy_timescaledb-1.0.1.dist-info/RECORD
